pyconn/__init__.py
pyconn/slack.py
pyconn/common/__init__.py
pyconn/common/util.py
pyconn/db/__init__.py
pyconn/db/advancedqreader.py
pyconn/db/kdb.py
pyconn/db/oracle.py
pyconn/db/qpool.py
pyconn/file/__init__.py
pyconn/file/csv.py
pyconn/file/excel.py
pyconn/wx/__init__.py
pyconn/wx/config.py
pyconn/wx/wechat.py
pyconn4-0.3.1.dist-info/LICENSE
pyconn4-0.3.1.dist-info/METADATA
pyconn4-0.3.1.dist-info/WHEEL
pyconn4-0.3.1.dist-info/top_level.txt
pyconn4-0.3.1.dist-info/RECORD
