Metadata-Version: 2.1
Name: pyconn4
Version: 0.3.1
Summary: python connection tools collection
Home-page: 
Author: James Liu
Author-email: liuchuanbo@gmail.com
License: Copyright (c) 2016, James Liu
License-File: LICENSE
Requires-Dist: qPython4==0.1.0
Requires-Dist: numpy==2.0.2
Requires-Dist: pandas==2.2.2
